setup.py
bin/wercker
wercker.egg-info/PKG-INFO
wercker.egg-info/SOURCES.txt
wercker.egg-info/dependency_links.txt
wercker.egg-info/requires.txt
wercker.egg-info/top_level.txt
werckercli/__init__.py
werckercli/authentication.py
werckercli/cli.py
werckercli/client.py
werckercli/config.py
werckercli/decorators.py
werckercli/git.py
werckercli/heroku.py
werckercli/metrics.py
werckercli/netrc.py
werckercli/paths.py
werckercli/printer.py
werckercli/prompt.py
werckercli/commands/__init__.py
werckercli/commands/build.py
werckercli/commands/clearsettings.py
werckercli/commands/create.py
werckercli/commands/login.py
werckercli/commands/project.py
werckercli/commands/services.py
werckercli/commands/target.py
werckercli/commands/update.py
werckercli/commands/validate.py
werckercli/tests/__init__.py
werckercli/tests/alltests.py
werckercli/tests/test_authentication.py
werckercli/tests/test_cli.py
werckercli/tests/test_client.py
werckercli/tests/test_config.py
werckercli/tests/test_decorators.py
werckercli/tests/test_git.py
werckercli/tests/test_heroku.py
werckercli/tests/test_metrics.py
werckercli/tests/test_paths.py
werckercli/tests/test_prompt.py
werckercli/tests/utils.py